tcShip/__init__.py
tcShip/tcShip.py
tcShip-0.0.1.dist-info/METADATA
tcShip-0.0.1.dist-info/WHEEL
tcShip-0.0.1.dist-info/top_level.txt
tcShip-0.0.1.dist-info/RECORD
