Metadata-Version: 2.1
Name: tcShip
Version: 0.0.1
Summary: python package for tcship race
Home-page: 
Author: gaoxiaos
Author-email: ai_hub@qq.com
License: MIT
Platform: UNKNOWN
Classifier: Programming Language :: Python :: 3
Classifier: License :: OSI Approved :: MIT License
Classifier: Operating System :: OS Independent
Requires-Dist: pygame (>=2.0.0)
